odoo/addons/message_auto_subscribe_notify_own/README.rst
odoo/addons/message_auto_subscribe_notify_own/__init__.py
odoo/addons/message_auto_subscribe_notify_own/__manifest__.py
odoo/addons/message_auto_subscribe_notify_own/i18n/message_auto_subscribe_notify_own.pot
odoo/addons/message_auto_subscribe_notify_own/models/__init__.py
odoo/addons/message_auto_subscribe_notify_own/models/auto_subscribe_notify_own_model.py
odoo/addons/message_auto_subscribe_notify_own/models/mail_thread.py
odoo/addons/message_auto_subscribe_notify_own/readme/CONFIGURE.rst
odoo/addons/message_auto_subscribe_notify_own/readme/CONTRIBUTORS.rst
odoo/addons/message_auto_subscribe_notify_own/readme/DESCRIPTION.rst
odoo/addons/message_auto_subscribe_notify_own/readme/USAGE.rst
odoo/addons/message_auto_subscribe_notify_own/security/ir.model.access.csv
odoo/addons/message_auto_subscribe_notify_own/static/description/icon.png
odoo/addons/message_auto_subscribe_notify_own/static/description/index.html
odoo/addons/message_auto_subscribe_notify_own/tests/__init__.py
odoo/addons/message_auto_subscribe_notify_own/tests/test_fake_model.py
odoo/addons/message_auto_subscribe_notify_own/tests/test_message_auto_subscribe_notify_own.py
odoo/addons/message_auto_subscribe_notify_own/views/auto_subscribe_notify_own_model.xml
odoo11_addon_message_auto_subscribe_notify_own-11.0.2.0.0.99.dev3.dist-info/METADATA
odoo11_addon_message_auto_subscribe_notify_own-11.0.2.0.0.99.dev3.dist-info/WHEEL
odoo11_addon_message_auto_subscribe_notify_own-11.0.2.0.0.99.dev3.dist-info/top_level.txt
odoo11_addon_message_auto_subscribe_notify_own-11.0.2.0.0.99.dev3.dist-info/RECORD
